flask_qrlabels/__init__.py
Flask_QRlabels-0.0.1.dist-info/LICENSE
Flask_QRlabels-0.0.1.dist-info/METADATA
Flask_QRlabels-0.0.1.dist-info/WHEEL
Flask_QRlabels-0.0.1.dist-info/top_level.txt
Flask_QRlabels-0.0.1.dist-info/RECORD
