Metadata-Version: 2.1
Name: Flask-QRlabels
Version: 0.0.1
License-File: LICENSE
Requires-Dist: flask-login
Requires-Dist: qrcode
Requires-Dist: Pillow
